procenv/__init__.py
procenv/applications.py
procenv/applications_test.py
procenv/checks.py
procenv/checks_test.py
procenv/cli.py
procenv/exceptions.py
procenv/utils.py
procenv/utils_test.py
procenv-0.1.2.dist-info/DESCRIPTION.rst
procenv-0.1.2.dist-info/METADATA
procenv-0.1.2.dist-info/RECORD
procenv-0.1.2.dist-info/WHEEL
procenv-0.1.2.dist-info/entry_points.txt
procenv-0.1.2.dist-info/metadata.json
procenv-0.1.2.dist-info/top_level.txt
