Metadata-Version: 2.0
Name: procenv
Version: 0.1.2
Summary: Run, manage and monitor Procfile-based applications
Home-page: https://github.com/sourcelair/procenv
Author: Paris Kasidiaris
Author-email: paris@sourcelair.com
License: MIT
Platform: UNKNOWN
Classifier: Development Status :: 4 - Beta
Classifier: Intended Audience :: Developers
Classifier: License :: OSI Approved :: MIT License
Classifier: Programming Language :: Python :: 3.6
Requires-Dist: honcho (>=1.0.0)
Requires-Dist: click (>=6.7.0)
